wejax/__init__.py
wejax/errors.py
wejax/fim.py
wejax/jacobian.py
wejax-1.0.1.dist-info/LICENSE
wejax-1.0.1.dist-info/METADATA
wejax-1.0.1.dist-info/WHEEL
wejax-1.0.1.dist-info/RECORD
